bsoft/__init__.py
bsoft/bibtex.py
bsoft/bsoft_logo.png
bsoft/constants.py
bsoft/convert.py
bsoft/protocols.conf
bsoft/wizards.py
bsoft/protocols/__init__.py
bsoft/protocols/protocol_bfilter.py
bsoft/protocols/protocol_blocres.py
bsoft/protocols/protocol_particle_pick.py
bsoft/tests/__init__.py
bsoft/tests/test_protocols_bsoft_blocres.py
bsoft/viewers/__init__.py
bsoft/viewers/bsoft_viewers.py
scipion_em_bsoft-3.0.6.dist-info/LICENSE
scipion_em_bsoft-3.0.6.dist-info/METADATA
scipion_em_bsoft-3.0.6.dist-info/WHEEL
scipion_em_bsoft-3.0.6.dist-info/entry_points.txt
scipion_em_bsoft-3.0.6.dist-info/top_level.txt
scipion_em_bsoft-3.0.6.dist-info/RECORD
