Metadata-Version: 2.1
Name: scipion-em-bsoft
Version: 3.0.6
Summary: Plugin to use Cryoef program within the Scipion framework
Home-page: https://github.com/scipion-em/scipion-em-bsoft
Author: I2PC
Author-email: scipion@cnb.csic.es
License: UNKNOWN
Keywords: scipion electron-microscopy cryo-em structural-biology image-processing scipion-3.0
Platform: UNKNOWN
Requires-Dist: scipion-em
